{"updated":"2026-07-21","source":"jquants-data prices (調整後終値ベース)","near_threshold":0.03,"stocks":[{"code":"1980","close":2608.0,"rebound":true,"levels":[{"id":"L1","label":"25日線","price":2782.3,"dist":0.0668,"hit":true},{"id":"L2","label":"25日線-5%","price":2643.2,"dist":0.0135,"hit":true},{"id":"L3","label":"25日線-8%","price":2559.7,"dist":-0.0185,"hit":false},{"id":"L4","label":"20日高値-10%","price":2672.1,"dist":0.0246,"hit":true},{"id":"L5","label":"20日高値-15%","price":2523.7,"dist":-0.0323,"hit":false},{"id":"L6","label":"60日安値","price":2357.0,"dist":-0.0962,"hit":false}]},{"code":"5016","close":3665.0,"rebound":true,"levels":[{"id":"L1","label":"25日線","price":4225.7,"dist":0.153,"hit":true},{"id":"L2","label":"25日線-5%","price":4014.4,"dist":0.0953,"hit":true},{"id":"L3","label":"25日線-8%","price":3887.6,"dist":0.0607,"hit":true},{"id":"L4","label":"20日高値-10%","price":4398.3,"dist":0.2001,"hit":true},{"id":"L5","label":"20日高値-15%","price":4153.9,"dist":0.1334,"hit":true},{"id":"L6","label":"60日安値","price":3341.0,"dist":-0.0884,"hit":false}]},{"code":"5830","close":3359.0,"rebound":true,"levels":[{"id":"L1","label":"25日線","price":3224.3,"dist":-0.0401,"hit":false},{"id":"L2","label":"25日線-5%","price":3063.1,"dist":-0.0881,"hit":false},{"id":"L3","label":"25日線-8%","price":2966.4,"dist":-0.1169,"hit":false},{"id":"L4","label":"20日高値-10%","price":3078.0,"dist":-0.0837,"hit":false},{"id":"L5","label":"20日高値-15%","price":2907.0,"dist":-0.1346,"hit":false},{"id":"L6","label":"60日安値","price":2895.5,"dist":-0.138,"hit":false}]},{"code":"6101","close":6800.0,"rebound":true,"levels":[{"id":"L1","label":"25日線","price":7545.6,"dist":0.1096,"hit":true},{"id":"L2","label":"25日線-5%","price":7168.3,"dist":0.0542,"hit":true},{"id":"L3","label":"25日線-8%","price":6942.0,"dist":0.0209,"hit":true},{"id":"L4","label":"20日高値-10%","price":7362.0,"dist":0.0826,"hit":true},{"id":"L5","label":"20日高値-15%","price":6953.0,"dist":0.0225,"hit":true},{"id":"L6","label":"60日安値","price":4120.0,"dist":-0.3941,"hit":false}],"tsureyasu":{"tier":"candidate","event":false,"self_r5":-0.0921,"sector":"3600","sector_r5":-0.0147,"resid":-0.0774,"tag":null}},{"code":"6590","close":5360.0,"rebound":true,"levels":[{"id":"L1","label":"25日線","price":5150.4,"dist":-0.0391,"hit":false},{"id":"L2","label":"25日線-5%","price":4892.9,"dist":-0.0871,"hit":false},{"id":"L3","label":"25日線-8%","price":4738.4,"dist":-0.116,"hit":false},{"id":"L4","label":"20日高値-10%","price":5382.0,"dist":0.0041,"hit":true},{"id":"L5","label":"20日高値-15%","price":5083.0,"dist":-0.0517,"hit":false},{"id":"L6","label":"60日安値","price":4275.0,"dist":-0.2024,"hit":false}]},{"code":"6617","close":7870.0,"rebound":true,"levels":[{"id":"L1","label":"25日線","price":7699.2,"dist":-0.0217,"hit":false},{"id":"L2","label":"25日線-5%","price":7314.2,"dist":-0.0706,"hit":false},{"id":"L3","label":"25日線-8%","price":7083.3,"dist":-0.1,"hit":false},{"id":"L4","label":"20日高値-10%","price":7461.0,"dist":-0.052,"hit":false},{"id":"L5","label":"20日高値-15%","price":7046.5,"dist":-0.1046,"hit":false},{"id":"L6","label":"60日安値","price":5520.0,"dist":-0.2986,"hit":false}]},{"code":"6814","close":7290.0,"rebound":true,"levels":[{"id":"L1","label":"25日線","price":6366.4,"dist":-0.1267,"hit":false},{"id":"L2","label":"25日線-5%","price":6048.1,"dist":-0.1704,"hit":false},{"id":"L3","label":"25日線-8%","price":5857.1,"dist":-0.1966,"hit":false},{"id":"L4","label":"20日高値-10%","price":6777.0,"dist":-0.0704,"hit":false},{"id":"L5","label":"20日高値-15%","price":6400.5,"dist":-0.122,"hit":false},{"id":"L6","label":"60日安値","price":5610.0,"dist":-0.2305,"hit":false}]},{"code":"6855","close":6360.0,"rebound":true,"levels":[{"id":"L1","label":"25日線","price":7569.6,"dist":0.1902,"hit":true},{"id":"L2","label":"25日線-5%","price":7191.1,"dist":0.1307,"hit":true},{"id":"L3","label":"25日線-8%","price":6964.0,"dist":0.095,"hit":true},{"id":"L4","label":"20日高値-10%","price":7929.0,"dist":0.2467,"hit":true},{"id":"L5","label":"20日高値-15%","price":7488.5,"dist":0.1774,"hit":true},{"id":"L6","label":"60日安値","price":5960.0,"dist":-0.0629,"hit":false}],"tsureyasu":{"tier":"candidate","event":false,"self_r5":-0.1167,"sector":"3650","sector_r5":-0.0219,"resid":-0.0948,"tag":null}},{"code":"6941","close":9000.0,"rebound":true,"levels":[{"id":"L1","label":"25日線","price":9529.6,"dist":0.0588,"hit":true},{"id":"L2","label":"25日線-5%","price":9053.1,"dist":0.0059,"hit":true},{"id":"L3","label":"25日線-8%","price":8767.2,"dist":-0.0259,"hit":false},{"id":"L4","label":"20日高値-10%","price":9792.0,"dist":0.088,"hit":true},{"id":"L5","label":"20日高値-15%","price":9248.0,"dist":0.0276,"hit":true},{"id":"L6","label":"60日安値","price":7930.0,"dist":-0.1189,"hit":false}]},{"code":"8377","close":7407.0,"rebound":true,"levels":[{"id":"L1","label":"25日線","price":7032.0,"dist":-0.0506,"hit":false},{"id":"L2","label":"25日線-5%","price":6680.4,"dist":-0.0981,"hit":false},{"id":"L3","label":"25日線-8%","price":6469.4,"dist":-0.1266,"hit":false},{"id":"L4","label":"20日高値-10%","price":6969.6,"dist":-0.0591,"hit":false},{"id":"L5","label":"20日高値-15%","price":6582.4,"dist":-0.1113,"hit":false},{"id":"L6","label":"60日安値","price":5602.0,"dist":-0.2437,"hit":false}]},{"code":"9880","close":3330.0,"rebound":true,"levels":[{"id":"L1","label":"25日線","price":3835.4,"dist":0.1518,"hit":true},{"id":"L2","label":"25日線-5%","price":3643.6,"dist":0.0942,"hit":true},{"id":"L3","label":"25日線-8%","price":3528.6,"dist":0.0596,"hit":true},{"id":"L4","label":"20日高値-10%","price":3879.0,"dist":0.1649,"hit":true},{"id":"L5","label":"20日高値-15%","price":3663.5,"dist":0.1002,"hit":true},{"id":"L6","label":"60日安値","price":2633.0,"dist":-0.2093,"hit":false}]}]}
