{"updated":"2026-07-22","source":"qdp-r2 fact_prices_daily (調整後四本値)","params":{"swing_n":4,"prom_atr":0.5,"life_days":120,"merge_pct":0.01,"atr_window":14,"max_levels":3,"touch_band_atr":0.5,"touch_cooldown":10,"reversal_atr":1.0,"react_days":5},"stocks":[{"code":"1980","close":2624.0,"support":[],"resistance":[2625.0,2694.0,2730.0],"support_touches":[],"resistance_touches":[3,8,1],"support_reversals":[],"resistance_reversals":[0,3,0]},{"code":"5016","close":3771.0,"support":[3606.0,3481.0,3350.0],"resistance":[4148.0,4335.0,4398.0],"support_touches":[5,3,3],"resistance_touches":[0,4,1],"support_reversals":[2,3,2],"resistance_reversals":[0,0,0]},{"code":"5830","close":3450.0,"support":[3427.0,3335.0,3298.0],"resistance":[3646.0],"support_touches":[1,3,3],"resistance_touches":[1],"support_reversals":[1,1,1],"resistance_reversals":[1]},{"code":"6101","close":6750.0,"support":[6700.0,5920.0,5610.0],"resistance":[6960.0,7050.0,8630.0],"support_touches":[3,0,0],"resistance_touches":[1,3,0],"support_reversals":[1,0,0],"resistance_reversals":[1,1,0]},{"code":"6590","close":5320.0,"support":[4440.0,4060.0,3930.0],"resistance":[5440.0,5520.0,5596.0],"support_touches":[7,1,3],"resistance_touches":[2,4,6],"support_reversals":[6,1,3],"resistance_reversals":[0,1,3]},{"code":"6617","close":8110.0,"support":[7150.0,6690.0,5450.0],"resistance":[8380.0,8550.0,8850.0],"support_touches":[2,0,2],"resistance_touches":[1,4,0],"support_reversals":[1,0,2],"resistance_reversals":[1,4,0]},{"code":"6814","close":7470.0,"support":[7420.0,7060.0,6690.0],"resistance":[7980.0,8700.0],"support_touches":[1,4,1],"resistance_touches":[1,0],"support_reversals":[1,1,0],"resistance_reversals":[0,0]},{"code":"6855","close":6500.0,"support":[6470.0,6350.0,6080.0],"resistance":[6550.0,7110.0,7250.0],"support_touches":[1,6,1],"resistance_touches":[2,5,7],"support_reversals":[1,3,1],"resistance_reversals":[2,0,2]},{"code":"6941","close":9380.0,"support":[9230.0,8090.0,7610.0],"resistance":[9640.0,10430.0,11300.0],"support_touches":[7,1,2],"resistance_touches":[7,2,2],"support_reversals":[5,1,2],"resistance_reversals":[5,1,2]},{"code":"8377","close":7540.0,"support":[6978.0,6800.0,6643.0],"resistance":[],"support_touches":[2,2,4],"resistance_touches":[],"support_reversals":[1,2,1],"resistance_reversals":[]},{"code":"9880","close":3390.0,"support":[2971.0,2939.0,2780.0],"resistance":[4625.0,4760.0,4915.0],"support_touches":[2,1,2],"resistance_touches":[0,1,0],"support_reversals":[1,0,1],"resistance_reversals":[0,1,0]}]}
